LICENSE.txt
MANIFEST.in
README.rst
setup.py
olekps/__init__.py
olekps.egg-info/PKG-INFO
olekps.egg-info/SOURCES.txt
olekps.egg-info/dependency_links.txt
olekps.egg-info/top_level.txt