Metadata-Version: 2.1
Name: olekps
Version: 1.0.0
Summary: lib olekps
Home-page: UNKNOWN
Author: olekps
Author-email: olekps.official@gmail.com
License: MIT
Keywords: olekps
Platform: UNKNOWN
Classifier: Development Status :: 5 - Production/Stable
Classifier: Intended Audience :: Education
Classifier: Operating System :: Microsoft :: Windows :: Windows 10
Classifier: License :: OSI Approved :: MIT License
Classifier: Programming Language :: Python :: 3
License-File: LICENSE.txt
